{
	"type": 3,
	"detail": {
		"name": "DraconicStare",
		"transname": "龙之凝视",
		"des": "巨龙的血统往往为后裔们带来福音...",
		"story": "巨龙的血脉，在带给龙裔们可怖外表的同时，也带给了他们威压的力量。",
		"function": "大幅减弱对手的属性值。"
	},
	"limit": {
		"level": 30,
		"job": [],
		"race": ["Elf","Half_Elf","Half_Orc","Human","Unknown","Tiefling"]
	},
	"element": "Normal",
	"consumeSP": 0,
	"hurt": {
		"HP": 10,
		"SP": 10,
		"cAtk": 10,
		"dAtk": 10,
		"Matk": 10,
		"Hit": 10,
		"Cri": 10,
		"Def": 10,
		"Mdef": 10,
		"Flee": 10,
		"Aspd": 10
	},
	"hurt_increase": {
		"HP": 10,
		"SP": 10,
		"cAtk": 10,
		"dAtk": 10,
		"Matk": 10,
		"Hit": 10,
		"Cri": 10,
		"Def": 10,
		"Mdef": 10,
		"Flee": 10,
		"Aspd": 10
	},
	"addition": {
		"HP": 0,
		"SP": 0,
		"cAtk": 0,
		"dAtk": 0,
		"Matk": 0,
		"Hit": 0,
		"Cri": 0,
		"Def": 10,
		"Mdef": 10,
		"Flee": 0,
		"Aspd": 0
	},
	"addition_percent": {
		"HP": 0,
		"SP": 0,
		"cAtk": 0,
		"dAtk": 0,
		"Matk": 0,
		"Hit": 0,
		"Cri": 0,
		"Def": 0,
		"Mdef": 0,
		"Flee": 0,
		"Aspd": 0
	}
}